[
  {
    "publicada": 1,
    "numero": 3590,
    "escrutado": true,
    "digitalizado": 1,
    "id_informacion_mesa_corporacion": "0104021020173590",
    "nombre_archivo": "https://elecciones-hnd-publicacion-prod-us-east-1.s3.us-east-1.amazonaws.com/ACTAS/04/0421035900041000.pdf?X-Amz-Algorithm=AWS4-HMAC-SHA256&X-Amz-Credential=AKIATNSYFO5EYDYMH46K%2F20251210%2Fus-east-1%2Fs3%2Faws4_request&X-Amz-Date=20251210T064106Z&X-Amz-Expires=7200&X-Amz-SignedHeaders=host&X-Amz-Signature=0f73078c7bb8205cf6ec40ff8939508d3a31730b6913f761f64086e16926c42d",
    "etiquetas": [
      "Divulgada Correctamente",
      "Pendiente de Revisión"
    ],
    "zona": "02",
    "needs_download": false
  },
  {
    "publicada": 1,
    "numero": 3591,
    "escrutado": true,
    "digitalizado": 1,
    "id_informacion_mesa_corporacion": "0104021020173591",
    "nombre_archivo": "https://elecciones-hnd-publicacion-prod-us-east-1.s3.us-east-1.amazonaws.com/ACTAS/04/0421035910041000.pdf?X-Amz-Algorithm=AWS4-HMAC-SHA256&X-Amz-Credential=AKIATNSYFO5EYDYMH46K%2F20251210%2Fus-east-1%2Fs3%2Faws4_request&X-Amz-Date=20251210T064106Z&X-Amz-Expires=7200&X-Amz-SignedHeaders=host&X-Amz-Signature=68e253094c404dce6e9585ed22f38422a260c1ffc319ee6643c7bfd9fa9ad1d4",
    "etiquetas": [
      "Divulgada Correctamente",
      "Pendiente de Revisión"
    ],
    "zona": "02",
    "needs_download": false
  }
]