[
  {
    "publicada": 1,
    "numero": 1970,
    "escrutado": true,
    "digitalizado": 1,
    "id_informacion_mesa_corporacion": "0103003020011970",
    "nombre_archivo": "https://elecciones-hnd-publicacion-prod-us-east-1.s3.us-east-1.amazonaws.com/E14/03/003/02/001/E14_P01_03_003_002_00_001_1970_0758.pdf?X-Amz-Algorithm=AWS4-HMAC-SHA256&X-Amz-Credential=AKIATNSYFO5EYDYMH46K%2F20251210%2Fus-east-1%2Fs3%2Faws4_request&X-Amz-Date=20251210T063842Z&X-Amz-Expires=7200&X-Amz-SignedHeaders=host&X-Amz-Signature=df3bc8b7b90d2c02c9f3a637e404aab2e2b97e8be21843d95d61bf7e64e74eb9",
    "etiquetas": [
      "Divulgada Correctamente",
      "Pendiente de Revisión"
    ],
    "zona": "02",
    "needs_download": false
  },
  {
    "publicada": 1,
    "numero": 1971,
    "escrutado": true,
    "digitalizado": 1,
    "id_informacion_mesa_corporacion": "0103003020011971",
    "nombre_archivo": "https://elecciones-hnd-publicacion-prod-us-east-1.s3.us-east-1.amazonaws.com/E14/03/003/02/001/E14_P01_03_003_002_00_001_1971_0758.pdf?X-Amz-Algorithm=AWS4-HMAC-SHA256&X-Amz-Credential=AKIATNSYFO5EYDYMH46K%2F20251210%2Fus-east-1%2Fs3%2Faws4_request&X-Amz-Date=20251210T063842Z&X-Amz-Expires=7200&X-Amz-SignedHeaders=host&X-Amz-Signature=31f41cb3f04ecd0180c8352275421c78e3534b47d71e6245ea46057f58ef773b",
    "etiquetas": [
      "Divulgada Correctamente",
      "Pendiente de Revisión"
    ],
    "zona": "02",
    "needs_download": false
  },
  {
    "publicada": 1,
    "numero": 1972,
    "escrutado": true,
    "digitalizado": 1,
    "id_informacion_mesa_corporacion": "0103003020011972",
    "nombre_archivo": "https://elecciones-hnd-publicacion-prod-us-east-1.s3.us-east-1.amazonaws.com/E14/03/003/02/001/E14_P01_03_003_002_00_001_1972_0758.pdf?X-Amz-Algorithm=AWS4-HMAC-SHA256&X-Amz-Credential=AKIATNSYFO5EYDYMH46K%2F20251210%2Fus-east-1%2Fs3%2Faws4_request&X-Amz-Date=20251210T063842Z&X-Amz-Expires=7200&X-Amz-SignedHeaders=host&X-Amz-Signature=a90ff8c7056e990a9d11c4807a0f282794d95af1a1704aef1452462ec932dcdc",
    "etiquetas": [
      "Inconsistencia",
      "Pendiente de Revisión"
    ],
    "zona": "02",
    "needs_download": false
  },
  {
    "publicada": 1,
    "numero": 1973,
    "escrutado": true,
    "digitalizado": 1,
    "id_informacion_mesa_corporacion": "0103003020011973",
    "nombre_archivo": "https://elecciones-hnd-publicacion-prod-us-east-1.s3.us-east-1.amazonaws.com/E14/03/003/02/001/E14_P01_03_003_002_00_001_1973_0758.pdf?X-Amz-Algorithm=AWS4-HMAC-SHA256&X-Amz-Credential=AKIATNSYFO5EYDYMH46K%2F20251210%2Fus-east-1%2Fs3%2Faws4_request&X-Amz-Date=20251210T063842Z&X-Amz-Expires=7200&X-Amz-SignedHeaders=host&X-Amz-Signature=bd85851b419e3f5e2b64d75e8346acc35f743121842f831c0c5cb954014ddc6b",
    "etiquetas": [
      "Divulgada Correctamente",
      "Pendiente de Revisión"
    ],
    "zona": "02",
    "needs_download": false
  },
  {
    "publicada": 1,
    "numero": 1974,
    "escrutado": true,
    "digitalizado": 1,
    "id_informacion_mesa_corporacion": "0103003020011974",
    "nombre_archivo": "https://elecciones-hnd-publicacion-prod-us-east-1.s3.us-east-1.amazonaws.com/E14/03/003/02/001/E14_P01_03_003_002_00_001_1974_0759.pdf?X-Amz-Algorithm=AWS4-HMAC-SHA256&X-Amz-Credential=AKIATNSYFO5EYDYMH46K%2F20251210%2Fus-east-1%2Fs3%2Faws4_request&X-Amz-Date=20251210T063842Z&X-Amz-Expires=7200&X-Amz-SignedHeaders=host&X-Amz-Signature=6413b1d503131ec01d8f7c542a6f1974a43b1b51ae98e4ca46189b46e1305250",
    "etiquetas": [
      "Divulgada Correctamente",
      "Pendiente de Revisión"
    ],
    "zona": "02",
    "needs_download": false
  },
  {
    "publicada": 1,
    "numero": 1975,
    "escrutado": true,
    "digitalizado": 1,
    "id_informacion_mesa_corporacion": "0103003020011975",
    "nombre_archivo": "https://elecciones-hnd-publicacion-prod-us-east-1.s3.us-east-1.amazonaws.com/E14/03/003/02/001/E14_P01_03_003_002_00_001_1975_0759.pdf?X-Amz-Algorithm=AWS4-HMAC-SHA256&X-Amz-Credential=AKIATNSYFO5EYDYMH46K%2F20251210%2Fus-east-1%2Fs3%2Faws4_request&X-Amz-Date=20251210T063842Z&X-Amz-Expires=7200&X-Amz-SignedHeaders=host&X-Amz-Signature=3f108f968e8580c99448a83cbd80d7c7023c09673a51b797ecc4e54de68f7591",
    "etiquetas": [
      "Divulgada Correctamente",
      "Pendiente de Revisión"
    ],
    "zona": "02",
    "needs_download": false
  },
  {
    "publicada": 1,
    "numero": 1976,
    "escrutado": true,
    "digitalizado": 1,
    "id_informacion_mesa_corporacion": "0103003020011976",
    "nombre_archivo": "https://elecciones-hnd-publicacion-prod-us-east-1.s3.us-east-1.amazonaws.com/E14/03/003/02/001/E14_P01_03_003_002_00_001_1976_0759.pdf?X-Amz-Algorithm=AWS4-HMAC-SHA256&X-Amz-Credential=AKIATNSYFO5EYDYMH46K%2F20251210%2Fus-east-1%2Fs3%2Faws4_request&X-Amz-Date=20251210T063842Z&X-Amz-Expires=7200&X-Amz-SignedHeaders=host&X-Amz-Signature=9155109c6b07d61ece27502d5d7034f62fccc4ae32a84f5c4f8fbcb4186b8d4d",
    "etiquetas": [
      "Divulgada Correctamente",
      "Pendiente de Revisión"
    ],
    "zona": "02",
    "needs_download": false
  },
  {
    "publicada": 1,
    "numero": 1977,
    "escrutado": true,
    "digitalizado": 1,
    "id_informacion_mesa_corporacion": "0103003020011977",
    "nombre_archivo": "https://elecciones-hnd-publicacion-prod-us-east-1.s3.us-east-1.amazonaws.com/E14/03/003/02/001/E14_P01_03_003_002_00_001_1977_0759.pdf?X-Amz-Algorithm=AWS4-HMAC-SHA256&X-Amz-Credential=AKIATNSYFO5EYDYMH46K%2F20251210%2Fus-east-1%2Fs3%2Faws4_request&X-Amz-Date=20251210T063842Z&X-Amz-Expires=7200&X-Amz-SignedHeaders=host&X-Amz-Signature=647dfd5a28e8dd72ac15b562320b642f8d28b6d5cfbf17ceb593084509fe5eda",
    "etiquetas": [
      "Divulgada Correctamente",
      "Pendiente de Revisión"
    ],
    "zona": "02",
    "needs_download": false
  }
]