[
  {
    "publicada": 1,
    "numero": 9670,
    "escrutado": true,
    "digitalizado": 1,
    "id_informacion_mesa_corporacion": "0108001011259670",
    "nombre_archivo": "https://elecciones-hnd-publicacion-prod-us-east-1.s3.us-east-1.amazonaws.com/E14/08/001/01/125/E14_P01_08_001_001_00_125_9670_3600.pdf?X-Amz-Algorithm=AWS4-HMAC-SHA256&X-Amz-Credential=AKIATNSYFO5EYDYMH46K%2F20251210%2Fus-east-1%2Fs3%2Faws4_request&X-Amz-Date=20251210T064742Z&X-Amz-Expires=7200&X-Amz-SignedHeaders=host&X-Amz-Signature=e9aa12ff4e72481f700578b12e02ea540480367f248bd1b19bc3c2abd3fb0920",
    "etiquetas": [
      "Divulgada Correctamente",
      "Pendiente de Revisión"
    ],
    "zona": "01",
    "needs_download": false
  },
  {
    "publicada": 1,
    "numero": 9671,
    "escrutado": true,
    "digitalizado": 1,
    "id_informacion_mesa_corporacion": "0108001011259671",
    "nombre_archivo": "https://elecciones-hnd-publicacion-prod-us-east-1.s3.us-east-1.amazonaws.com/E14/08/001/01/125/E14_P01_08_001_001_00_125_9671_3600.pdf?X-Amz-Algorithm=AWS4-HMAC-SHA256&X-Amz-Credential=AKIATNSYFO5EYDYMH46K%2F20251210%2Fus-east-1%2Fs3%2Faws4_request&X-Amz-Date=20251210T064742Z&X-Amz-Expires=7200&X-Amz-SignedHeaders=host&X-Amz-Signature=fdb252668c47a681102e0fc9e13741f7fd2c33ff179528f293f452f5505fdfa1",
    "etiquetas": [
      "Divulgada Correctamente",
      "Pendiente de Revisión"
    ],
    "zona": "01",
    "needs_download": false
  },
  {
    "publicada": 1,
    "numero": 9672,
    "escrutado": true,
    "digitalizado": 1,
    "id_informacion_mesa_corporacion": "0108001011259672",
    "nombre_archivo": "https://elecciones-hnd-publicacion-prod-us-east-1.s3.us-east-1.amazonaws.com/E14/08/001/01/125/E14_P01_08_001_001_00_125_9672_3600.pdf?X-Amz-Algorithm=AWS4-HMAC-SHA256&X-Amz-Credential=AKIATNSYFO5EYDYMH46K%2F20251210%2Fus-east-1%2Fs3%2Faws4_request&X-Amz-Date=20251210T064742Z&X-Amz-Expires=7200&X-Amz-SignedHeaders=host&X-Amz-Signature=8ea8c38e9a9a274de6a74d594420f6e263b16c3f6012711dc07d990ef5dc5795",
    "etiquetas": [
      "Divulgada Correctamente",
      "Pendiente de Revisión"
    ],
    "zona": "01",
    "needs_download": false
  },
  {
    "publicada": 1,
    "numero": 9673,
    "escrutado": true,
    "digitalizado": 1,
    "id_informacion_mesa_corporacion": "0108001011259673",
    "nombre_archivo": "https://elecciones-hnd-publicacion-prod-us-east-1.s3.us-east-1.amazonaws.com/E14/08/001/01/125/E14_P01_08_001_001_00_125_9673_3600.pdf?X-Amz-Algorithm=AWS4-HMAC-SHA256&X-Amz-Credential=AKIATNSYFO5EYDYMH46K%2F20251210%2Fus-east-1%2Fs3%2Faws4_request&X-Amz-Date=20251210T064742Z&X-Amz-Expires=7200&X-Amz-SignedHeaders=host&X-Amz-Signature=9ebe88f349d06d07dc416287f413480eec09a206ec56b16e2a5abfeb50d0f3f0",
    "etiquetas": [
      "Divulgada Correctamente",
      "Pendiente de Revisión"
    ],
    "zona": "01",
    "needs_download": false
  },
  {
    "publicada": 1,
    "numero": 9674,
    "escrutado": true,
    "digitalizado": 1,
    "id_informacion_mesa_corporacion": "0108001011259674",
    "nombre_archivo": "https://elecciones-hnd-publicacion-prod-us-east-1.s3.us-east-1.amazonaws.com/E14/08/001/01/125/E14_P01_08_001_001_00_125_9674_3601.pdf?X-Amz-Algorithm=AWS4-HMAC-SHA256&X-Amz-Credential=AKIATNSYFO5EYDYMH46K%2F20251210%2Fus-east-1%2Fs3%2Faws4_request&X-Amz-Date=20251210T064742Z&X-Amz-Expires=7200&X-Amz-SignedHeaders=host&X-Amz-Signature=0148c9d3e2b008cd9fb738edce9f41558487f0317909240544314bbf7d9a7423",
    "etiquetas": [
      "Inconsistencia",
      "Pendiente de Revisión"
    ],
    "zona": "01",
    "needs_download": false
  },
  {
    "publicada": 1,
    "numero": 9675,
    "escrutado": true,
    "digitalizado": 1,
    "id_informacion_mesa_corporacion": "0108001011259675",
    "nombre_archivo": "https://elecciones-hnd-publicacion-prod-us-east-1.s3.us-east-1.amazonaws.com/E14/08/001/01/125/E14_P01_08_001_001_00_125_9675_3601.pdf?X-Amz-Algorithm=AWS4-HMAC-SHA256&X-Amz-Credential=AKIATNSYFO5EYDYMH46K%2F20251210%2Fus-east-1%2Fs3%2Faws4_request&X-Amz-Date=20251210T064742Z&X-Amz-Expires=7200&X-Amz-SignedHeaders=host&X-Amz-Signature=b89d68c7571fca90f595a1fb3e2488e9e2f7b8a4d86a143d3d47b5b9fcd14a42",
    "etiquetas": [
      "Divulgada Correctamente",
      "Pendiente de Revisión"
    ],
    "zona": "01",
    "needs_download": false
  },
  {
    "publicada": 1,
    "numero": 9676,
    "escrutado": true,
    "digitalizado": 1,
    "id_informacion_mesa_corporacion": "0108001011259676",
    "nombre_archivo": "https://elecciones-hnd-publicacion-prod-us-east-1.s3.us-east-1.amazonaws.com/E14/08/001/01/125/E14_P01_08_001_001_00_125_9676_3601.pdf?X-Amz-Algorithm=AWS4-HMAC-SHA256&X-Amz-Credential=AKIATNSYFO5EYDYMH46K%2F20251210%2Fus-east-1%2Fs3%2Faws4_request&X-Amz-Date=20251210T064742Z&X-Amz-Expires=7200&X-Amz-SignedHeaders=host&X-Amz-Signature=6fb8d0e33b20f5440680f1498fc7166d328308c04ea7a93c1691bba09b8f26d9",
    "etiquetas": [
      "Divulgada Correctamente",
      "Pendiente de Revisión"
    ],
    "zona": "01",
    "needs_download": false
  },
  {
    "publicada": 1,
    "numero": 9677,
    "escrutado": true,
    "digitalizado": 1,
    "id_informacion_mesa_corporacion": "0108001011259677",
    "nombre_archivo": "https://elecciones-hnd-publicacion-prod-us-east-1.s3.us-east-1.amazonaws.com/E14/08/001/01/125/E14_P01_08_001_001_00_125_9677_3601.pdf?X-Amz-Algorithm=AWS4-HMAC-SHA256&X-Amz-Credential=AKIATNSYFO5EYDYMH46K%2F20251210%2Fus-east-1%2Fs3%2Faws4_request&X-Amz-Date=20251210T064742Z&X-Amz-Expires=7200&X-Amz-SignedHeaders=host&X-Amz-Signature=9ff333e15b5b7d940c3adfadc1c570ff0f83d5283014454be041271ca772789a",
    "etiquetas": [
      "Divulgada Correctamente",
      "Pendiente de Revisión"
    ],
    "zona": "01",
    "needs_download": false
  }
]