{
  "recibidas": {
    "n": "352",
    "l": "Tres Cinco Dos"
  },
  "sobrantes": {
    "n": "164",
    "l": "Uno Seis Cuatro"
  },
  "usadas": {
    "n": "188",
    "l": "Uno Ocho Ocho"
  },
  "total_votantes": {
    "n": "188",
    "l": "Uno Ocho Ocho"
  },
  "partido_dc": {
    "n": "002",
    "l": "Cero Cero Dos"
  },
  "partido_libre": {
    "n": "031",
    "l": "Cero Tres Uno"
  },
  "partido_pinu": {
    "n": "002",
    "l": "Cero Cero Dos"
  },
  "partido_plh": {
    "n": "109",
    "l": "Uno Cero Nueve"
  },
  "partido_pnh": {
    "n": "044",
    "l": "Cero Cuatro Cuatro"
  },
  "en_blanco": {
    "n": "000",
    "l": "Cero Cero Cero"
  },
  "nulos": {
    "n": "000",
    "l": "Cero Cero Cero"
  },
  "gran_total": {
    "n": "188",
    "l": "Uno Ocho Ocho"
  }
}