{
  "recibidas": {
    "n": "350",
    "l": "tres cinco cero"
  },
  "sobrantes": {
    "n": "148",
    "l": "uno cuatro ocho"
  },
  "usadas": {
    "n": "202",
    "l": "dos cero dos"
  },
  "total_votantes": {
    "n": "202",
    "l": "dos cero dos"
  },
  "partido_dc": {
    "n": "000",
    "l": "cero cero cero"
  },
  "partido_libre": {
    "n": "033",
    "l": "cero tres tres"
  },
  "partido_pinu": {
    "n": "004",
    "l": "cero cero cuatro"
  },
  "partido_plh": {
    "n": "075",
    "l": "cero siete cinco"
  },
  "partido_pnh": {
    "n": "081",
    "l": "cero ocho uno"
  },
  "en_blanco": {
    "n": "004",
    "l": "cero cero cuatro"
  },
  "nulos": {
    "n": "005",
    "l": "cero cero cinco"
  },
  "gran_total": {
    "n": "202",
    "l": "dos cero dos"
  }
}