{
  "recibidas": {
    "n": "268",
    "l": "Dos Seis Ocho"
  },
  "sobrantes": {
    "n": "143",
    "l": "Uno Cuatro Tres"
  },
  "usadas": {
    "n": "125",
    "l": "Uno Dos Cinco"
  },
  "total_votantes": {
    "n": "125",
    "l": "Uno Dos Cinco"
  },
  "partido_dc": {
    "n": "000",
    "l": "Cero Cero Cero"
  },
  "partido_libre": {
    "n": "009",
    "l": "Cero Cero Nueve"
  },
  "partido_pinu": {
    "n": "000",
    "l": "Cero Cero Cero"
  },
  "partido_plh": {
    "n": "057",
    "l": "Cero Cinco Siete"
  },
  "partido_pnh": {
    "n": "055",
    "l": "Cero Cinco Cinco"
  },
  "en_blanco": {
    "n": "000",
    "l": "Cero Cero Cero"
  },
  "nulos": {
    "n": "004",
    "l": "Cero Cero Cuatro"
  },
  "gran_total": {
    "n": "125",
    "l": "Uno Dos Cinco"
  }
}