[
  {
    "publicada": 1,
    "numero": 18940,
    "escrutado": true,
    "digitalizado": 1,
    "id_informacion_mesa_corporacion": "01180080100218940",
    "nombre_archivo": "https://elecciones-hnd-publicacion-prod-us-east-1.s3.us-east-1.amazonaws.com/E14/18/008/01/002/E14_P01_18_008_001_00_002_18940_7570.pdf?X-Amz-Algorithm=AWS4-HMAC-SHA256&X-Amz-Credential=AKIATNSYFO5EYDYMH46K%2F20251210%2Fus-east-1%2Fs3%2Faws4_request&X-Amz-Date=20251210T070016Z&X-Amz-Expires=7200&X-Amz-SignedHeaders=host&X-Amz-Signature=dc74c3869a01cf88fe16952ec761251d8711d67d7d28713014b6f4899225ff07",
    "etiquetas": [
      "Divulgada Correctamente",
      "Pendiente de Revisión"
    ],
    "zona": "01",
    "needs_download": false
  },
  {
    "publicada": 1,
    "numero": 18941,
    "escrutado": true,
    "digitalizado": 1,
    "id_informacion_mesa_corporacion": "01180080100218941",
    "nombre_archivo": "https://elecciones-hnd-publicacion-prod-us-east-1.s3.us-east-1.amazonaws.com/E14/18/008/01/002/E14_P01_18_008_001_00_002_18941_7570.pdf?X-Amz-Algorithm=AWS4-HMAC-SHA256&X-Amz-Credential=AKIATNSYFO5EYDYMH46K%2F20251210%2Fus-east-1%2Fs3%2Faws4_request&X-Amz-Date=20251210T070016Z&X-Amz-Expires=7200&X-Amz-SignedHeaders=host&X-Amz-Signature=f194eaea5cade591279084ce9c95c298526639dde7fcc5fc19d96ca5296360fe",
    "etiquetas": [
      "Divulgada Correctamente",
      "Pendiente de Revisión"
    ],
    "zona": "01",
    "needs_download": false
  },
  {
    "publicada": 1,
    "numero": 18942,
    "escrutado": true,
    "digitalizado": 1,
    "id_informacion_mesa_corporacion": "01180080100218942",
    "nombre_archivo": "https://elecciones-hnd-publicacion-prod-us-east-1.s3.us-east-1.amazonaws.com/E14/18/008/01/002/E14_P01_18_008_001_00_002_18942_7570.pdf?X-Amz-Algorithm=AWS4-HMAC-SHA256&X-Amz-Credential=AKIATNSYFO5EYDYMH46K%2F20251210%2Fus-east-1%2Fs3%2Faws4_request&X-Amz-Date=20251210T070016Z&X-Amz-Expires=7200&X-Amz-SignedHeaders=host&X-Amz-Signature=f4b887746ce7e2013b540321cfa54ac2e194be7d4549325429073e6925c54a8c",
    "etiquetas": [
      "Divulgada Correctamente",
      "Pendiente de Revisión"
    ],
    "zona": "01",
    "needs_download": false
  },
  {
    "publicada": 1,
    "numero": 18943,
    "escrutado": true,
    "digitalizado": 1,
    "id_informacion_mesa_corporacion": "01180080100218943",
    "nombre_archivo": "https://elecciones-hnd-publicacion-prod-us-east-1.s3.us-east-1.amazonaws.com/E14/18/008/01/002/E14_P01_18_008_001_00_002_18943_7570.pdf?X-Amz-Algorithm=AWS4-HMAC-SHA256&X-Amz-Credential=AKIATNSYFO5EYDYMH46K%2F20251210%2Fus-east-1%2Fs3%2Faws4_request&X-Amz-Date=20251210T070016Z&X-Amz-Expires=7200&X-Amz-SignedHeaders=host&X-Amz-Signature=455d4e17a72805db65555e453edbfaf5460c4e7053de18d8b53133392c87e551",
    "etiquetas": [
      "Divulgada Correctamente",
      "Pendiente de Revisión"
    ],
    "zona": "01",
    "needs_download": false
  },
  {
    "publicada": 1,
    "numero": 18944,
    "escrutado": true,
    "digitalizado": 1,
    "id_informacion_mesa_corporacion": "01180080100218944",
    "nombre_archivo": "https://elecciones-hnd-publicacion-prod-us-east-1.s3.us-east-1.amazonaws.com/E14/18/008/01/002/E14_P01_18_008_001_00_002_18944_7571.pdf?X-Amz-Algorithm=AWS4-HMAC-SHA256&X-Amz-Credential=AKIATNSYFO5EYDYMH46K%2F20251210%2Fus-east-1%2Fs3%2Faws4_request&X-Amz-Date=20251210T070016Z&X-Amz-Expires=7200&X-Amz-SignedHeaders=host&X-Amz-Signature=9fb502bd149bf44e2f5b3c9da0354a7082e39c9f9be696ebd41d04f7c8a5ecc2",
    "etiquetas": [
      "Divulgada Correctamente",
      "Pendiente de Revisión"
    ],
    "zona": "01",
    "needs_download": false
  },
  {
    "publicada": 1,
    "numero": 18945,
    "escrutado": true,
    "digitalizado": 1,
    "id_informacion_mesa_corporacion": "01180080100218945",
    "nombre_archivo": "https://elecciones-hnd-publicacion-prod-us-east-1.s3.us-east-1.amazonaws.com/E14/18/008/01/002/E14_P01_18_008_001_00_002_18945_7571.pdf?X-Amz-Algorithm=AWS4-HMAC-SHA256&X-Amz-Credential=AKIATNSYFO5EYDYMH46K%2F20251210%2Fus-east-1%2Fs3%2Faws4_request&X-Amz-Date=20251210T070016Z&X-Amz-Expires=7200&X-Amz-SignedHeaders=host&X-Amz-Signature=83fdde5fee62b5d48bdca43e5b913fc76bdb1e3f7210d170055db79e709ebc9e",
    "etiquetas": [
      "Divulgada Correctamente",
      "Pendiente de Revisión"
    ],
    "zona": "01",
    "needs_download": false
  },
  {
    "publicada": 1,
    "numero": 18946,
    "escrutado": true,
    "digitalizado": 1,
    "id_informacion_mesa_corporacion": "01180080100218946",
    "nombre_archivo": "https://elecciones-hnd-publicacion-prod-us-east-1.s3.us-east-1.amazonaws.com/ACTAS/18/1808189460041000.pdf?X-Amz-Algorithm=AWS4-HMAC-SHA256&X-Amz-Credential=AKIATNSYFO5EYDYMH46K%2F20251210%2Fus-east-1%2Fs3%2Faws4_request&X-Amz-Date=20251210T070016Z&X-Amz-Expires=7200&X-Amz-SignedHeaders=host&X-Amz-Signature=e5e3290b0c6d5144c4dec0256fbed60ed31e2760790702f791bef71cb027dd13",
    "etiquetas": [
      "Inconsistencia",
      "Pendiente de Revisión"
    ],
    "zona": "01",
    "needs_download": false
  }
]