[
  {
    "publicada": 1,
    "numero": 3172,
    "escrutado": true,
    "digitalizado": 1,
    "id_informacion_mesa_corporacion": "0104009020043172",
    "nombre_archivo": "https://elecciones-hnd-publicacion-prod-us-east-1.s3.us-east-1.amazonaws.com/E14/04/009/02/004/E14_P01_04_009_002_00_004_3172_1284.pdf?X-Amz-Algorithm=AWS4-HMAC-SHA256&X-Amz-Credential=AKIATNSYFO5EYDYMH46K%2F20251210%2Fus-east-1%2Fs3%2Faws4_request&X-Amz-Date=20251210T064021Z&X-Amz-Expires=7200&X-Amz-SignedHeaders=host&X-Amz-Signature=fcaabf6c98818366ee38637af0170f6cc034f5f8a70f013385a8b0ab5770ec6f",
    "etiquetas": [
      "Divulgada Correctamente",
      "Pendiente de Revisión"
    ],
    "zona": "02",
    "needs_download": false
  }
]