[
  {
    "publicada": 1,
    "numero": 9992,
    "escrutado": true,
    "digitalizado": 1,
    "id_informacion_mesa_corporacion": "0108001012169992",
    "nombre_archivo": "https://elecciones-hnd-publicacion-prod-us-east-1.s3.us-east-1.amazonaws.com/E14/08/001/01/216/E14_P01_08_001_001_00_216_9992_3693.pdf?X-Amz-Algorithm=AWS4-HMAC-SHA256&X-Amz-Credential=AKIATNSYFO5EYDYMH46K%2F20251210%2Fus-east-1%2Fs3%2Faws4_request&X-Amz-Date=20251210T064737Z&X-Amz-Expires=7200&X-Amz-SignedHeaders=host&X-Amz-Signature=5ffa1a8dffaef276ad2963fd4c5c2e49f51efd863e77ee39d728f13d22ca777d",
    "etiquetas": [
      "Divulgada Correctamente",
      "Pendiente de Revisión"
    ],
    "zona": "01",
    "needs_download": false
  },
  {
    "publicada": 1,
    "numero": 9993,
    "escrutado": true,
    "digitalizado": 1,
    "id_informacion_mesa_corporacion": "0108001012169993",
    "nombre_archivo": "https://elecciones-hnd-publicacion-prod-us-east-1.s3.us-east-1.amazonaws.com/E14/08/001/01/216/E14_P01_08_001_001_00_216_9993_3693.pdf?X-Amz-Algorithm=AWS4-HMAC-SHA256&X-Amz-Credential=AKIATNSYFO5EYDYMH46K%2F20251210%2Fus-east-1%2Fs3%2Faws4_request&X-Amz-Date=20251210T064737Z&X-Amz-Expires=7200&X-Amz-SignedHeaders=host&X-Amz-Signature=68c83af35c682a429071ecb2652ff0332395b61bf855a2fca69775a2442a5e2c",
    "etiquetas": [
      "Divulgada Correctamente",
      "Pendiente de Revisión"
    ],
    "zona": "01",
    "needs_download": false
  },
  {
    "publicada": 1,
    "numero": 9994,
    "escrutado": true,
    "digitalizado": 1,
    "id_informacion_mesa_corporacion": "0108001012169994",
    "nombre_archivo": "https://elecciones-hnd-publicacion-prod-us-east-1.s3.us-east-1.amazonaws.com/E14/08/001/01/216/E14_P01_08_001_001_00_216_9994_3693.pdf?X-Amz-Algorithm=AWS4-HMAC-SHA256&X-Amz-Credential=AKIATNSYFO5EYDYMH46K%2F20251210%2Fus-east-1%2Fs3%2Faws4_request&X-Amz-Date=20251210T064737Z&X-Amz-Expires=7200&X-Amz-SignedHeaders=host&X-Amz-Signature=eb81f74a8d105787fe3d860b4ef66213975ed025b3896a8bdbeeb73d69ba9041",
    "etiquetas": [
      "Divulgada Correctamente",
      "Pendiente de Revisión"
    ],
    "zona": "01",
    "needs_download": false
  },
  {
    "publicada": 1,
    "numero": 9995,
    "escrutado": true,
    "digitalizado": 1,
    "id_informacion_mesa_corporacion": "0108001012169995",
    "nombre_archivo": "https://elecciones-hnd-publicacion-prod-us-east-1.s3.us-east-1.amazonaws.com/E14/08/001/01/216/E14_P01_08_001_001_00_216_9995_3693.pdf?X-Amz-Algorithm=AWS4-HMAC-SHA256&X-Amz-Credential=AKIATNSYFO5EYDYMH46K%2F20251210%2Fus-east-1%2Fs3%2Faws4_request&X-Amz-Date=20251210T064737Z&X-Amz-Expires=7200&X-Amz-SignedHeaders=host&X-Amz-Signature=8b97a9181c057ac6b50a88daffe0c02ca1f8c2a5d7bb1201d5d7ac414d1731a8",
    "etiquetas": [
      "Divulgada Correctamente",
      "Pendiente de Revisión"
    ],
    "zona": "01",
    "needs_download": false
  },
  {
    "publicada": 1,
    "numero": 9996,
    "escrutado": true,
    "digitalizado": 1,
    "id_informacion_mesa_corporacion": "0108001012169996",
    "nombre_archivo": "https://elecciones-hnd-publicacion-prod-us-east-1.s3.us-east-1.amazonaws.com/E14/08/001/01/216/E14_P01_08_001_001_00_216_9996_3694.pdf?X-Amz-Algorithm=AWS4-HMAC-SHA256&X-Amz-Credential=AKIATNSYFO5EYDYMH46K%2F20251210%2Fus-east-1%2Fs3%2Faws4_request&X-Amz-Date=20251210T064737Z&X-Amz-Expires=7200&X-Amz-SignedHeaders=host&X-Amz-Signature=f33e07693b77b9e07309803542226e7b2dd7a19dcc0a0ee4dde09b0663a34c55",
    "etiquetas": [
      "Inconsistencia",
      "Pendiente de Revisión"
    ],
    "zona": "01",
    "needs_download": false
  },
  {
    "publicada": 1,
    "numero": 9997,
    "escrutado": true,
    "digitalizado": 1,
    "id_informacion_mesa_corporacion": "0108001012169997",
    "nombre_archivo": "https://elecciones-hnd-publicacion-prod-us-east-1.s3.us-east-1.amazonaws.com/E14/08/001/01/216/E14_P01_08_001_001_00_216_9997_3694.pdf?X-Amz-Algorithm=AWS4-HMAC-SHA256&X-Amz-Credential=AKIATNSYFO5EYDYMH46K%2F20251210%2Fus-east-1%2Fs3%2Faws4_request&X-Amz-Date=20251210T064737Z&X-Amz-Expires=7200&X-Amz-SignedHeaders=host&X-Amz-Signature=d8d3246493eb0269bc307473cc3f81a70829707e50c678696914ff49ac3912f7",
    "etiquetas": [
      "Divulgada Correctamente",
      "Pendiente de Revisión"
    ],
    "zona": "01",
    "needs_download": false
  },
  {
    "publicada": 1,
    "numero": 9998,
    "escrutado": true,
    "digitalizado": 1,
    "id_informacion_mesa_corporacion": "0108001012169998",
    "nombre_archivo": "https://elecciones-hnd-publicacion-prod-us-east-1.s3.us-east-1.amazonaws.com/E14/08/001/01/216/E14_P01_08_001_001_00_216_9998_3694.pdf?X-Amz-Algorithm=AWS4-HMAC-SHA256&X-Amz-Credential=AKIATNSYFO5EYDYMH46K%2F20251210%2Fus-east-1%2Fs3%2Faws4_request&X-Amz-Date=20251210T064737Z&X-Amz-Expires=7200&X-Amz-SignedHeaders=host&X-Amz-Signature=56d0416777e276ea884663a7aeebcff3eb72e82d33b6a5b88f49187e0285222d",
    "etiquetas": [
      "Divulgada Correctamente",
      "Pendiente de Revisión"
    ],
    "zona": "01",
    "needs_download": false
  },
  {
    "publicada": 1,
    "numero": 9999,
    "escrutado": true,
    "digitalizado": 1,
    "id_informacion_mesa_corporacion": "0108001012169999",
    "nombre_archivo": "https://elecciones-hnd-publicacion-prod-us-east-1.s3.us-east-1.amazonaws.com/ACTAS/08/0801099990041000.pdf?X-Amz-Algorithm=AWS4-HMAC-SHA256&X-Amz-Credential=AKIATNSYFO5EYDYMH46K%2F20251210%2Fus-east-1%2Fs3%2Faws4_request&X-Amz-Date=20251210T064737Z&X-Amz-Expires=7200&X-Amz-SignedHeaders=host&X-Amz-Signature=442d9195ea74d394452eb6388a16c2097cc86664fa96dfc485c55b6e23cd8038",
    "etiquetas": [
      "Divulgada Correctamente",
      "Pendiente de Revisión"
    ],
    "zona": "01",
    "needs_download": false
  },
  {
    "publicada": 1,
    "numero": 10000,
    "escrutado": true,
    "digitalizado": 1,
    "id_informacion_mesa_corporacion": "01080010121610000",
    "nombre_archivo": "https://elecciones-hnd-publicacion-prod-us-east-1.s3.us-east-1.amazonaws.com/ACTAS/08/0801100000041000.pdf?X-Amz-Algorithm=AWS4-HMAC-SHA256&X-Amz-Credential=AKIATNSYFO5EYDYMH46K%2F20251210%2Fus-east-1%2Fs3%2Faws4_request&X-Amz-Date=20251210T064737Z&X-Amz-Expires=7200&X-Amz-SignedHeaders=host&X-Amz-Signature=a934bc3786f93f68a4761800349666d230b2236291ee4cd092288d79cb182a58",
    "etiquetas": [
      "Inconsistencia",
      "Pendiente de Revisión"
    ],
    "zona": "01",
    "needs_download": false
  },
  {
    "publicada": 1,
    "numero": 10001,
    "escrutado": true,
    "digitalizado": 1,
    "id_informacion_mesa_corporacion": "01080010121610001",
    "nombre_archivo": "https://elecciones-hnd-publicacion-prod-us-east-1.s3.us-east-1.amazonaws.com/ACTAS/08/0801100010041000.pdf?X-Amz-Algorithm=AWS4-HMAC-SHA256&X-Amz-Credential=AKIATNSYFO5EYDYMH46K%2F20251210%2Fus-east-1%2Fs3%2Faws4_request&X-Amz-Date=20251210T064737Z&X-Amz-Expires=7200&X-Amz-SignedHeaders=host&X-Amz-Signature=30813135ac02a9727dd8c27b2c70a8bcef7e0040b37cd48d76446bb55993f804",
    "etiquetas": [
      "Divulgada Correctamente",
      "Pendiente de Revisión"
    ],
    "zona": "01",
    "needs_download": false
  },
  {
    "publicada": 1,
    "numero": 10002,
    "escrutado": true,
    "digitalizado": 1,
    "id_informacion_mesa_corporacion": "01080010121610002",
    "nombre_archivo": "https://elecciones-hnd-publicacion-prod-us-east-1.s3.us-east-1.amazonaws.com/E14/08/001/01/216/E14_P01_08_001_001_00_216_10002_3696.pdf?X-Amz-Algorithm=AWS4-HMAC-SHA256&X-Amz-Credential=AKIATNSYFO5EYDYMH46K%2F20251210%2Fus-east-1%2Fs3%2Faws4_request&X-Amz-Date=20251210T064737Z&X-Amz-Expires=7200&X-Amz-SignedHeaders=host&X-Amz-Signature=6707da9d3704be471d322d7cb022e7b7fc099b2ab68d0fd2943512ca10e6d4bc",
    "etiquetas": [
      "Inconsistencia",
      "Pendiente de Revisión"
    ],
    "zona": "01",
    "needs_download": false
  },
  {
    "publicada": 1,
    "numero": 10003,
    "escrutado": true,
    "digitalizado": 1,
    "id_informacion_mesa_corporacion": "01080010121610003",
    "nombre_archivo": "https://elecciones-hnd-publicacion-prod-us-east-1.s3.us-east-1.amazonaws.com/E14/08/001/01/216/E14_P01_08_001_001_00_216_10003_3696.pdf?X-Amz-Algorithm=AWS4-HMAC-SHA256&X-Amz-Credential=AKIATNSYFO5EYDYMH46K%2F20251210%2Fus-east-1%2Fs3%2Faws4_request&X-Amz-Date=20251210T064737Z&X-Amz-Expires=7200&X-Amz-SignedHeaders=host&X-Amz-Signature=0e3e98a0bbbbb8429e275bcd8317cc570b38bd830f166b51bf34c091f461177e",
    "etiquetas": [
      "Divulgada Correctamente",
      "Pendiente de Revisión"
    ],
    "zona": "01",
    "needs_download": false
  },
  {
    "publicada": 1,
    "numero": 10004,
    "escrutado": true,
    "digitalizado": 1,
    "id_informacion_mesa_corporacion": "01080010121610004",
    "nombre_archivo": "https://elecciones-hnd-publicacion-prod-us-east-1.s3.us-east-1.amazonaws.com/E14/08/001/01/216/E14_P01_08_001_001_00_216_10004_3696.pdf?X-Amz-Algorithm=AWS4-HMAC-SHA256&X-Amz-Credential=AKIATNSYFO5EYDYMH46K%2F20251210%2Fus-east-1%2Fs3%2Faws4_request&X-Amz-Date=20251210T064737Z&X-Amz-Expires=7200&X-Amz-SignedHeaders=host&X-Amz-Signature=358893f36ab13691f8f5ba2778147154819414ef1720f900c8363602df47c6d5",
    "etiquetas": [
      "Divulgada Correctamente",
      "Pendiente de Revisión"
    ],
    "zona": "01",
    "needs_download": false
  }
]