[
  {
    "publicada": 1,
    "numero": 9172,
    "escrutado": true,
    "digitalizado": 1,
    "id_informacion_mesa_corporacion": "0108001010019172",
    "nombre_archivo": "https://elecciones-hnd-publicacion-prod-us-east-1.s3.us-east-1.amazonaws.com/E14/08/001/01/001/E14_P01_08_001_001_00_001_9172_3455.pdf?X-Amz-Algorithm=AWS4-HMAC-SHA256&X-Amz-Credential=AKIATNSYFO5EYDYMH46K%2F20251210%2Fus-east-1%2Fs3%2Faws4_request&X-Amz-Date=20251210T064721Z&X-Amz-Expires=7200&X-Amz-SignedHeaders=host&X-Amz-Signature=8fafebb4825bf5f544a36fb0fc7b06e47120bbce9fc4b4f36906d946c4ef8b10",
    "etiquetas": [
      "Divulgada Correctamente",
      "Pendiente de Revisión"
    ],
    "zona": "01",
    "needs_download": false
  },
  {
    "publicada": 1,
    "numero": 9173,
    "escrutado": true,
    "digitalizado": 1,
    "id_informacion_mesa_corporacion": "0108001010019173",
    "nombre_archivo": "https://elecciones-hnd-publicacion-prod-us-east-1.s3.us-east-1.amazonaws.com/E14/08/001/01/001/E14_P01_08_001_001_00_001_9173_3455.pdf?X-Amz-Algorithm=AWS4-HMAC-SHA256&X-Amz-Credential=AKIATNSYFO5EYDYMH46K%2F20251210%2Fus-east-1%2Fs3%2Faws4_request&X-Amz-Date=20251210T064721Z&X-Amz-Expires=7200&X-Amz-SignedHeaders=host&X-Amz-Signature=93133ebf6d93855c401367d72564cda7df80eb3bf5249f4b6d5db1ffdf2e27d0",
    "etiquetas": [
      "Divulgada Correctamente",
      "Pendiente de Revisión"
    ],
    "zona": "01",
    "needs_download": false
  },
  {
    "publicada": 1,
    "numero": 9174,
    "escrutado": true,
    "digitalizado": 1,
    "id_informacion_mesa_corporacion": "0108001010019174",
    "nombre_archivo": "https://elecciones-hnd-publicacion-prod-us-east-1.s3.us-east-1.amazonaws.com/E14/08/001/01/001/E14_P01_08_001_001_00_001_9174_3455.pdf?X-Amz-Algorithm=AWS4-HMAC-SHA256&X-Amz-Credential=AKIATNSYFO5EYDYMH46K%2F20251210%2Fus-east-1%2Fs3%2Faws4_request&X-Amz-Date=20251210T064721Z&X-Amz-Expires=7200&X-Amz-SignedHeaders=host&X-Amz-Signature=5d040b03e398b85adec099c3e342fbb4d27bce8feeee406b4aed0c724cc64e76",
    "etiquetas": [
      "Divulgada Correctamente",
      "Pendiente de Revisión"
    ],
    "zona": "01",
    "needs_download": false
  },
  {
    "publicada": 1,
    "numero": 9175,
    "escrutado": true,
    "digitalizado": 1,
    "id_informacion_mesa_corporacion": "0108001010019175",
    "nombre_archivo": "https://elecciones-hnd-publicacion-prod-us-east-1.s3.us-east-1.amazonaws.com/E14/08/001/01/001/E14_P01_08_001_001_00_001_9175_3455.pdf?X-Amz-Algorithm=AWS4-HMAC-SHA256&X-Amz-Credential=AKIATNSYFO5EYDYMH46K%2F20251210%2Fus-east-1%2Fs3%2Faws4_request&X-Amz-Date=20251210T064721Z&X-Amz-Expires=7200&X-Amz-SignedHeaders=host&X-Amz-Signature=ae123f9a9b5e282604ca85cb8a525a1efffec8c0208153bcfe489312e2149d6a",
    "etiquetas": [
      "Divulgada Correctamente",
      "Pendiente de Revisión"
    ],
    "zona": "01",
    "needs_download": false
  },
  {
    "publicada": 1,
    "numero": 9176,
    "escrutado": true,
    "digitalizado": 1,
    "id_informacion_mesa_corporacion": "0108001010019176",
    "nombre_archivo": "https://elecciones-hnd-publicacion-prod-us-east-1.s3.us-east-1.amazonaws.com/ACTAS/08/0801091760041000.pdf?X-Amz-Algorithm=AWS4-HMAC-SHA256&X-Amz-Credential=AKIATNSYFO5EYDYMH46K%2F20251210%2Fus-east-1%2Fs3%2Faws4_request&X-Amz-Date=20251210T064721Z&X-Amz-Expires=7200&X-Amz-SignedHeaders=host&X-Amz-Signature=39ab5f273d2ca88e108664964d569a7406572318babfaf789817e1c22e2b16bd",
    "etiquetas": [
      "Divulgada Correctamente",
      "Pendiente de Revisión"
    ],
    "zona": "01",
    "needs_download": false
  },
  {
    "publicada": 1,
    "numero": 9177,
    "escrutado": true,
    "digitalizado": 1,
    "id_informacion_mesa_corporacion": "0108001010019177",
    "nombre_archivo": "https://elecciones-hnd-publicacion-prod-us-east-1.s3.us-east-1.amazonaws.com/ACTAS/08/0801091770041000.pdf?X-Amz-Algorithm=AWS4-HMAC-SHA256&X-Amz-Credential=AKIATNSYFO5EYDYMH46K%2F20251210%2Fus-east-1%2Fs3%2Faws4_request&X-Amz-Date=20251210T064721Z&X-Amz-Expires=7200&X-Amz-SignedHeaders=host&X-Amz-Signature=eb49a8726dff8908bc496c3139a194088413f0a01d27d6ae430838b2e41f0e24",
    "etiquetas": [
      "Divulgada Correctamente",
      "Pendiente de Revisión"
    ],
    "zona": "01",
    "needs_download": false
  },
  {
    "publicada": 1,
    "numero": 9178,
    "escrutado": true,
    "digitalizado": 1,
    "id_informacion_mesa_corporacion": "0108001010019178",
    "nombre_archivo": "https://elecciones-hnd-publicacion-prod-us-east-1.s3.us-east-1.amazonaws.com/ACTAS/08/0801091780041000.pdf?X-Amz-Algorithm=AWS4-HMAC-SHA256&X-Amz-Credential=AKIATNSYFO5EYDYMH46K%2F20251210%2Fus-east-1%2Fs3%2Faws4_request&X-Amz-Date=20251210T064721Z&X-Amz-Expires=7200&X-Amz-SignedHeaders=host&X-Amz-Signature=b8f52098672267444e6a009df443051331bbe2063fb0ed23080bb38d097efff2",
    "etiquetas": [
      "Inconsistencia",
      "Pendiente de Revisión"
    ],
    "zona": "01",
    "needs_download": false
  },
  {
    "publicada": 1,
    "numero": 9179,
    "escrutado": true,
    "digitalizado": 1,
    "id_informacion_mesa_corporacion": "0108001010019179",
    "nombre_archivo": "https://elecciones-hnd-publicacion-prod-us-east-1.s3.us-east-1.amazonaws.com/E14/08/001/01/001/E14_P01_08_001_001_00_001_9179_3457.pdf?X-Amz-Algorithm=AWS4-HMAC-SHA256&X-Amz-Credential=AKIATNSYFO5EYDYMH46K%2F20251210%2Fus-east-1%2Fs3%2Faws4_request&X-Amz-Date=20251210T064721Z&X-Amz-Expires=7200&X-Amz-SignedHeaders=host&X-Amz-Signature=b389c1f82ebb2e9e4d830e8176074cd6e1cba7c31e27f0a5240608e3c8d7ecb8",
    "etiquetas": [
      "Inconsistencia",
      "Pendiente de Revisión"
    ],
    "zona": "01",
    "needs_download": false
  },
  {
    "publicada": 1,
    "numero": 9180,
    "escrutado": true,
    "digitalizado": 1,
    "id_informacion_mesa_corporacion": "0108001010019180",
    "nombre_archivo": "https://elecciones-hnd-publicacion-prod-us-east-1.s3.us-east-1.amazonaws.com/E14/08/001/01/001/E14_P01_08_001_001_00_001_9180_3457.pdf?X-Amz-Algorithm=AWS4-HMAC-SHA256&X-Amz-Credential=AKIATNSYFO5EYDYMH46K%2F20251210%2Fus-east-1%2Fs3%2Faws4_request&X-Amz-Date=20251210T064721Z&X-Amz-Expires=7200&X-Amz-SignedHeaders=host&X-Amz-Signature=5da50ebe0f7ba25811b8fc5f6b5b376b6512d6419d38b064daa45b5ae8137fe4",
    "etiquetas": [
      "Divulgada Correctamente",
      "Pendiente de Revisión"
    ],
    "zona": "01",
    "needs_download": false
  },
  {
    "publicada": 1,
    "numero": 9181,
    "escrutado": true,
    "digitalizado": 1,
    "id_informacion_mesa_corporacion": "0108001010019181",
    "nombre_archivo": "https://elecciones-hnd-publicacion-prod-us-east-1.s3.us-east-1.amazonaws.com/E14/08/001/01/001/E14_P01_08_001_001_00_001_9181_3457.pdf?X-Amz-Algorithm=AWS4-HMAC-SHA256&X-Amz-Credential=AKIATNSYFO5EYDYMH46K%2F20251210%2Fus-east-1%2Fs3%2Faws4_request&X-Amz-Date=20251210T064721Z&X-Amz-Expires=7200&X-Amz-SignedHeaders=host&X-Amz-Signature=f64c012f38aac9aac586992c3b5457c9512510e2a7c3ccdd37ae4a99e87b4e26",
    "etiquetas": [
      "Divulgada Correctamente",
      "Pendiente de Revisión"
    ],
    "zona": "01",
    "needs_download": false
  },
  {
    "publicada": 1,
    "numero": 9182,
    "escrutado": true,
    "digitalizado": 1,
    "id_informacion_mesa_corporacion": "0108001010019182",
    "nombre_archivo": "https://elecciones-hnd-publicacion-prod-us-east-1.s3.us-east-1.amazonaws.com/ACTAS/08/0801091820041000.pdf?X-Amz-Algorithm=AWS4-HMAC-SHA256&X-Amz-Credential=AKIATNSYFO5EYDYMH46K%2F20251210%2Fus-east-1%2Fs3%2Faws4_request&X-Amz-Date=20251210T064721Z&X-Amz-Expires=7200&X-Amz-SignedHeaders=host&X-Amz-Signature=de3679e5a2b901d747898bedc8b1bf1265df09f7924ee6c6f46254f74937b650",
    "etiquetas": [
      "Divulgada Correctamente",
      "Pendiente de Revisión"
    ],
    "zona": "01",
    "needs_download": false
  },
  {
    "publicada": 1,
    "numero": 9183,
    "escrutado": true,
    "digitalizado": 1,
    "id_informacion_mesa_corporacion": "0108001010019183",
    "nombre_archivo": "https://elecciones-hnd-publicacion-prod-us-east-1.s3.us-east-1.amazonaws.com/ACTAS/08/0801091830041000.pdf?X-Amz-Algorithm=AWS4-HMAC-SHA256&X-Amz-Credential=AKIATNSYFO5EYDYMH46K%2F20251210%2Fus-east-1%2Fs3%2Faws4_request&X-Amz-Date=20251210T064721Z&X-Amz-Expires=7200&X-Amz-SignedHeaders=host&X-Amz-Signature=8851add74c006d48d351f28aa838e4ab1f0d67f42e78c13a1e5360af0b66ce17",
    "etiquetas": [
      "Divulgada Correctamente",
      "Pendiente de Revisión"
    ],
    "zona": "01",
    "needs_download": false
  },
  {
    "publicada": 1,
    "numero": 9184,
    "escrutado": true,
    "digitalizado": 1,
    "id_informacion_mesa_corporacion": "0108001010019184",
    "nombre_archivo": "https://elecciones-hnd-publicacion-prod-us-east-1.s3.us-east-1.amazonaws.com/ACTAS/08/0801091840041000.pdf?X-Amz-Algorithm=AWS4-HMAC-SHA256&X-Amz-Credential=AKIATNSYFO5EYDYMH46K%2F20251210%2Fus-east-1%2Fs3%2Faws4_request&X-Amz-Date=20251210T064721Z&X-Amz-Expires=7200&X-Amz-SignedHeaders=host&X-Amz-Signature=cca88e1df02fb972836bd242e7943a26c63f0138b636fe002491ba51e4a928b4",
    "etiquetas": [
      "Divulgada Correctamente",
      "Pendiente de Revisión"
    ],
    "zona": "01",
    "needs_download": false
  }
]